flaskomponent/__init__.py
flaskomponent/css.py
flaskomponent/elements.py
flaskomponent-0.1.0.dist-info/METADATA
flaskomponent-0.1.0.dist-info/WHEEL
flaskomponent-0.1.0.dist-info/top_level.txt
flaskomponent-0.1.0.dist-info/RECORD
