Metadata-Version: 2.1
Name: flaskomponent
Version: 0.1.0
Summary: Add your description here
Requires-Python: >=3.12
Requires-Dist: flask >=3.0.3
